setup.py
symboldoc.py
symboldoc.egg-info/PKG-INFO
symboldoc.egg-info/SOURCES.txt
symboldoc.egg-info/dependency_links.txt
symboldoc.egg-info/entry_points.txt
symboldoc.egg-info/top_level.txt