Metadata-Version: 1.0
Name: symboldoc
Version: 0.0.1
Summary: Create docstrings based on module symbols
Home-page: https://github.com/fmartingr/symboldoc
Author: Felipe Martin
Author-email: me@fmartingr.com
License: MIT
Keywords: ast abstract syntax tree method class symbol docstring
Platform: UNKNOWN
